.hgignore
.hgtags
README.txt
setup.py
docs/HISTORY.txt
src/bethel/__init__.py
src/bethel.silva.purge.egg-info/PKG-INFO
src/bethel.silva.purge.egg-info/SOURCES.txt
src/bethel.silva.purge.egg-info/dependency_links.txt
src/bethel.silva.purge.egg-info/entry_points.txt
src/bethel.silva.purge.egg-info/namespace_packages.txt
src/bethel.silva.purge.egg-info/not-zip-safe
src/bethel.silva.purge.egg-info/requires.txt
src/bethel.silva.purge.egg-info/top_level.txt
src/bethel/silva/__init__.py
src/bethel/silva/purge/__init__.py
src/bethel/silva/purge/broom.png
src/bethel/silva/purge/configure.zcml
src/bethel/silva/purge/interfaces.py
src/bethel/silva/purge/purge.py
src/bethel/silva/purge/purgingServiceAdd.zpt
src/bethel/silva/purge/service.py
src/bethel/silva/purge/tests/PurgingTestCase.py
src/bethel/silva/purge/tests/__init__.py
src/bethel/silva/purge/tests/layer.py
src/bethel/silva/purge/tests/test_purge.py
src/bethel/silva/purge/tests/test_service.py
src/bethel/silva/purge/tests/grok/__init__.py
src/bethel/silva/purge/tests/grok/purge_events.py