Metadata-Version: 1.0
Name: bethel.silva.purge
Version: 1.0b
Summary: Send HTTP PURGE to caching servers on content publishing events
Home-page: http://pypi.python.org/pypi/bethel.silva.purge
Author: Andy Altepeter
Author-email: aaltepet@bethel.edu
License: GPL
Keywords: silva varnish cache purge
Platform: UNKNOWN
Classifier: Programming Language :: Python
